Metadata-Version: 1.0
Name: xblock-openedx-utils
Version: 0.9.0
Summary: Various utilities for XBlocks
Home-page: https://github.com/Stanford-Online
Author: Stanford OpenEdX
Author-email: dev@lagunita.stanford.edu
License: AGPL-3.0
Platform: UNKNOWN
